[{"id": 136, "name": "Samsung 970 EVO SSD", "price": 74235.15, "quantity": 74, "category": null, "fromCity": "Эльче", "isAvailable": "0", "views": 27977, "version": 3}, {"id": 155, "name": "delightful lip balm", "price": 99.98, "quantity": 1008, "category": "cosmetics", "fromCity": "Подгорица", "isAvailable": "1", "views": 16806, "version": 1}, {"id": 72, "name": "magnificent plumbing", "price": 90.74, "quantity": 1340, "category": "tools", "fromCity": "Бургос", "isAvailable": "1", "views": 5151, "version": 9}, {"id": 169, "name": "exquisite saw", "price": 88.2, "quantity": 962, "category": "tools", "fromCity": "Вальядолид", "isAvailable": "1", "views": 25974, "version": 3}, {"id": 117, "name": "tasteful tile", "price": 80.17658459104, "quantity": 1029, "category": "tools", "fromCity": "Монсон", "isAvailable": "1", "views": 15664, "version": 11}, {"id": 179, "name": "gorgeous night cream", "price": 79.06, "quantity": 693, "category": "cosmetics", "fromCity": "Тарраса", "isAvailable": "0", "views": 15026, "version": 0}, {"id": 66, "name": "beautiful hair mask", "price": 77.14380000000001, "quantity": 1712, "category": "cosmetics", "fromCity": "Сантьяго-де-Компостела", "isAvailable": "0", "views": 8566, "version": 9}, {"id": 129, "name": "sublime raspberry", "price": 59.1955, "quantity": 1384, "category": "fruit", "fromCity": "Мартоса", "isAvailable": "0", "views": 12752, "version": 7}, {"id": 204, "name": "amazing peach", "price": 56.45, "quantity": 946, "category": "fruit", "fromCity": "Навалькарнеро", "isAvailable": "1", "views": 10671, "version": 2}]