<?xml version="1.0" encoding="utf-8"?>
<clothing-items>
 <clothing>
  <id>
   266327938
  </id>
  <name>
   New Balance Hat O-4369
  </name>
  <category>
   Hat
  </category>
  <size>
   XXL
  </size>
  <color>
   Красный
  </color>
  <material>
   Полиэстер
  </material>
  <price>
   445229
  </price>
  <rating>
   4.88
  </rating>
  <reviews>
   603003
  </reviews>
  <new>
   +
  </new>
  <exclusive>
   no
  </exclusive>
 </clothing>
 <clothing>
  <id>
   485018451
  </id>
  <name>
   Fila Sweater S-5827
  </name>
  <category>
   Sweater
  </category>
  <size>
   XXL
  </size>
  <color>
   Желтый
  </color>
  <material>
   Полиэстер
  </material>
  <price>
   207374
  </price>
  <rating>
   3.93
  </rating>
  <reviews>
   824598
  </reviews>
  <exclusive>
   yes
  </exclusive>
  <sporty>
   no
  </sporty>
 </clothing>
 <clothing>
  <id>
   680649562
  </id>
  <name>
   Nike T-shirt N-6317
  </name>
  <category>
   T-shirt
  </category>
  <size>
   XL
  </size>
  <color>
   Зеленый
  </color>
  <material>
   Полиэстер
  </material>
  <price>
   431269
  </price>
  <rating>
   4.05
  </rating>
  <reviews>
   159291
  </reviews>
  <new>
   -
  </new>
 </clothing>
 <clothing>
  <id>
   618411259
  </id>
  <name>
   Brooks Skirt R-7776
  </name>
  <category>
   Skirt
  </category>
  <size>
   XL
  </size>
  <color>
   Зеленый
  </color>
  <material>
   Полиэстер
  </material>
  <price>
   574040
  </price>
  <rating>
   2.84
  </rating>
  <reviews>
   94402
  </reviews>
  <sporty>
   no
  </sporty>
 </clothing>
 <clothing>
  <id>
   456233883
  </id>
  <name>
   Brooks Handbags W-1503
  </name>
  <category>
   Handbags
  </category>
  <size>
   XXL
  </size>
  <color>
   Красный
  </color>
  <material>
   Шелк
  </material>
  <price>
   695294
  </price>
  <rating>
   4.99
  </rating>
  <reviews>
   432116
  </reviews>
  <new>
   +
  </new>
  <exclusive>
   no
  </exclusive>
  <sporty>
   yes
  </sporty>
 </clothing>
 <clothing>
  <id>
   693485461
  </id>
  <name>
   Puma Belts L-8632
  </name>
  <category>
   Belts
  </category>
  <size>
   L
  </size>
  <color>
   Голубой
  </color>
  <material>
   Кожа
  </material>
  <price>
   894070
  </price>
  <rating>
   3.22
  </rating>
  <reviews>
   777738
  </reviews>
  <new>
   +
  </new>
  <exclusive>
   no
  </exclusive>
 </clothing>
 <clothing>
  <id>
   167009731
  </id>
  <name>
   Reebok Sweater N-1974
  </name>
  <category>
   Sweater
  </category>
  <size>
   XXL
  </size>
  <color>
   Оранжевый
  </color>
  <material>
   Шерсть
  </material>
  <price>
   872858
  </price>
  <rating>
   2.74
  </rating>
  <reviews>
   337694
  </reviews>
  <new>
   +
  </new>
  <exclusive>
   no
  </exclusive>
 </clothing>
 <clothing>
  <id>
   643340814
  </id>
  <name>
   Under Armour Gloves T-1059
  </name>
  <category>
   Gloves
  </category>
  <size>
   M
  </size>
  <color>
   Фиолетовый
  </color>
  <material>
   Вискоза
  </material>
  <price>
   497069
  </price>
  <rating>
   2.55
  </rating>
  <reviews>
   595173
  </reviews>
  <new>
   +
  </new>
  <sporty>
   no
  </sporty>
 </clothing>
 <clothing>
  <id>
   630814866
  </id>
  <name>
   Brooks Gloves S-2559
  </name>
  <category>
   Gloves
  </category>
  <size>
   M
  </size>
  <color>
   Оранжевый
  </color>
  <material>
   Хлопок
  </material>
  <price>
   367827
  </price>
  <rating>
   2.37
  </rating>
  <reviews>
   3072
  </reviews>
  <sporty>
   no
  </sporty>
 </clothing>
 <clothing>
  <id>
   585728030
  </id>
  <name>
   Puma T-shirt W-7743
  </name>
  <category>
   T-shirt
  </category>
  <size>
   XXL
  </size>
  <color>
   Желтый
  </color>
  <material>
   Лен
  </material>
  <price>
   972079
  </price>
  <rating>
   3.71
  </rating>
  <reviews>
   454710
  </reviews>
  <new>
   -
  </new>
  <sporty>
   yes
  </sporty>
 </clothing>
 <clothing>
  <id>
   733333807
  </id>
  <name>
   Reebok Shoes H-2228
  </name>
  <category>
   Shoes
  </category>
  <size>
   M
  </size>
  <color>
   Зеленый
  </color>
  <material>
   Хлопок
  </material>
  <price>
   362321
  </price>
  <rating>
   1.79
  </rating>
  <reviews>
   515572
  </reviews>
  <new>
   -
  </new>
  <sporty>
   no
  </sporty>
 </clothing>
 <clothing>
  <id>
   762353132
  </id>
  <name>
   Fila Belts L-3605
  </name>
  <category>
   Belts
  </category>
  <size>
   XXL
  </size>
  <color>
   Голубой
  </color>
  <material>
   Шерсть
  </material>
  <price>
   750713
  </price>
  <rating>
   4.78
  </rating>
  <reviews>
   6673
  </reviews>
  <exclusive>
   no
  </exclusive>
 </clothing>
 <clothing>
  <id>
   681614636
  </id>
  <name>
   Ellesse Umbrellas C-3490
  </name>
  <category>
   Umbrellas
  </category>
  <size>
   M
  </size>
  <color>
   Оранжевый
  </color>
  <material>
   Хлопок
  </material>
  <price>
   387852
  </price>
  <rating>
   3.17
  </rating>
  <reviews>
   307049
  </reviews>
  <new>
   +
  </new>
  <exclusive>
   yes
  </exclusive>
 </clothing>
 <clothing>
  <id>
   858570197
  </id>
  <name>
   PleinSport Sweater L-4084
  </name>
  <category>
   Sweater
  </category>
  <size>
   L
  </size>
  <color>
   Синий
  </color>
  <material>
   Хлопок
  </material>
  <price>
   697270
  </price>
  <rating>
   2.26
  </rating>
  <reviews>
   643190
  </reviews>
  <exclusive>
   yes
  </exclusive>
  <sporty>
   yes
  </sporty>
 </clothing>
 <clothing>
  <id>
   554793784
  </id>
  <name>
   Fila Dress Y-1777
  </name>
  <category>
   Dress
  </category>
  <size>
   M
  </size>
  <color>
   Красный
  </color>
  <material>
   Шелк
  </material>
  <price>
   925743
  </price>
  <rating>
   3.3
  </rating>
  <reviews>
   374590
  </reviews>
  <exclusive>
   no
  </exclusive>
 </clothing>
 <clothing>
  <id>
   876370217
  </id>
  <name>
   New Balance Umbrellas S-6697
  </name>
  <category>
   Umbrellas
  </category>
  <size>
   XL
  </size>
  <color>
   Оранжевый
  </color>
  <material>
   Вискоза
  </material>
  <price>
   292184
  </price>
  <rating>
   2.85
  </rating>
  <reviews>
   80043
  </reviews>
 </clothing>
 <clothing>
  <id>
   506184561
  </id>
  <name>
   Adidas Shoes X-5481
  </name>
  <category>
   Shoes
  </category>
  <size>
   M
  </size>
  <color>
   Голубой
  </color>
  <material>
   Шелк
  </material>
  <price>
   938828
  </price>
  <rating>
   3.12
  </rating>
  <reviews>
   698391
  </reviews>
  <new>
   +
  </new>
  <exclusive>
   no
  </exclusive>
  <sporty>
   no
  </sporty>
 </clothing>
 <clothing>
  <id>
   352563759
  </id>
  <name>
   PleinSport Hat Z-9334
  </name>
  <category>
   Hat
  </category>
  <size>
   M
  </size>
  <color>
   Фиолетовый
  </color>
  <material>
   Шелк
  </material>
  <price>
   612649
  </price>
  <rating>
   3.71
  </rating>
  <reviews>
   739814
  </reviews>
  <new>
   +
  </new>
 </clothing>
 <clothing>
  <id>
   945457791
  </id>
  <name>
   Nike Jeans K-4397
  </name>
  <category>
   Jeans
  </category>
  <size>
   S
  </size>
  <color>
   Желтый
  </color>
  <material>
   Шерсть
  </material>
  <price>
   751748
  </price>
  <rating>
   2.33
  </rating>
  <reviews>
   915724
  </reviews>
  <new>
   +
  </new>
  <exclusive>
   no
  </exclusive>
  <sporty>
   yes
  </sporty>
 </clothing>
 <clothing>
  <id>
   442341279
  </id>
  <name>
   Addidas Shoes R-9504
  </name>
  <category>
   Shoes
  </category>
  <size>
   M
  </size>
  <color>
   Зеленый
  </color>
  <material>
   Лен
  </material>
  <price>
   964093
  </price>
  <rating>
   3.7
  </rating>
  <reviews>
   755435
  </reviews>
  <sporty>
   yes
  </sporty>
 </clothing>
 <clothing>
  <id>
   443501382
  </id>
  <name>
   Asics Jeans L-7826
  </name>
  <category>
   Jeans
  </category>
  <size>
   XXL
  </size>
  <color>
   Синий
  </color>
  <material>
   Вискоза
  </material>
  <price>
   844589
  </price>
  <rating>
   3.49
  </rating>
  <reviews>
   970921
  </reviews>
  <new>
   +
  </new>
  <sporty>
   no
  </sporty>
 </clothing>
 <clothing>
  <id>
   549667372
  </id>
  <name>
   Lacoste Jacket A-3447
  </name>
  <category>
   Jacket
  </category>
  <size>
   XXL
  </size>
  <color>
   Красный
  </color>
  <material>
   Хлопок
  </material>
  <price>
   167686
  </price>
  <rating>
   2.42
  </rating>
  <reviews>
   998855
  </reviews>
  <new>
   -
  </new>
  <exclusive>
   no
  </exclusive>
  <sporty>
   no
  </sporty>
 </clothing>
 <clothing>
  <id>
   587475048
  </id>
  <name>
   Fila Pants P-7700
  </name>
  <category>
   Pants
  </category>
  <size>
   S
  </size>
  <color>
   Синий
  </color>
  <material>
   Шерсть
  </material>
  <price>
   895435
  </price>
  <rating>
   2.81
  </rating>
  <reviews>
   788697
  </reviews>
 </clothing>
 <clothing>
  <id>
   531569452
  </id>
  <name>
   Puma Blouse D-4297
  </name>
  <category>
   Blouse
  </category>
  <size>
   S
  </size>
  <color>
   Зеленый
  </color>
  <material>
   Нейлон
  </material>
  <price>
   497928
  </price>
  <rating>
   2.16
  </rating>
  <reviews>
   420371
  </reviews>
  <exclusive>
   no
  </exclusive>
 </clothing>
 <clothing>
  <id>
   949023950
  </id>
  <name>
   PleinSport Gloves G-5892
  </name>
  <category>
   Gloves
  </category>
  <size>
   M
  </size>
  <color>
   Голубой
  </color>
  <material>
   Вискоза
  </material>
  <price>
   601194
  </price>
  <rating>
   3.23
  </rating>
  <reviews>
   747094
  </reviews>
  <exclusive>
   no
  </exclusive>
 </clothing>
 <clothing>
  <id>
   701234066
  </id>
  <name>
   New Balance Pants F-2085
  </name>
  <category>
   Pants
  </category>
  <size>
   L
  </size>
  <color>
   Фиолетовый
  </color>
  <material>
   Шелк
  </material>
  <price>
   248289
  </price>
  <rating>
   3.25
  </rating>
  <reviews>
   721638
  </reviews>
 </clothing>
 <clothing>
  <id>
   344117193
  </id>
  <name>
   Nike Pants O-1520
  </name>
  <category>
   Pants
  </category>
  <size>
   S
  </size>
  <color>
   Синий
  </color>
  <material>
   Шелк
  </material>
  <price>
   892055
  </price>
  <rating>
   2.75
  </rating>
  <reviews>
   153769
  </reviews>
  <new>
   +
  </new>
  <sporty>
   no
  </sporty>
 </clothing>
 <clothing>
  <id>
   711994560
  </id>
  <name>
   Lacoste Shirt Z-9249
  </name>
  <category>
   Shirt
  </category>
  <size>
   XL
  </size>
  <color>
   Красный
  </color>
  <material>
   Хлопок
  </material>
  <price>
   671467
  </price>
  <rating>
   2.22
  </rating>
  <reviews>
   219145
  </reviews>
  <exclusive>
   no
  </exclusive>
  <sporty>
   yes
  </sporty>
 </clothing>
 <clothing>
  <id>
   944996879
  </id>
  <name>
   PleinSport Socks N-4079
  </name>
  <category>
   Socks
  </category>
  <size>
   L
  </size>
  <color>
   Фиолетовый
  </color>
  <material>
   Лен
  </material>
  <price>
   380195
  </price>
  <rating>
   2.61
  </rating>
  <reviews>
   441340
  </reviews>
  <new>
   +
  </new>
  <exclusive>
   no
  </exclusive>
  <sporty>
   yes
  </sporty>
 </clothing>
 <clothing>
  <id>
   176067085
  </id>
  <name>
   Vans Shirt C-2990
  </name>
  <category>
   Shirt
  </category>
  <size>
   S
  </size>
  <color>
   Фиолетовый
  </color>
  <material>
   Вискоза
  </material>
  <price>
   967379
  </price>
  <rating>
   4.56
  </rating>
  <reviews>
   923907
  </reviews>
  <sporty>
   no
  </sporty>
 </clothing>
 <clothing>
  <id>
   721960464
  </id>
  <name>
   New Balance Dress S-9564
  </name>
  <category>
   Dress
  </category>
  <size>
   S
  </size>
  <color>
   Зеленый
  </color>
  <material>
   Вискоза
  </material>
  <price>
   460138
  </price>
  <rating>
   1.6
  </rating>
  <reviews>
   504010
  </reviews>
  <new>
   +
  </new>
  <exclusive>
   yes
  </exclusive>
  <sporty>
   yes
  </sporty>
 </clothing>
 <clothing>
  <id>
   835030037
  </id>
  <name>
   Addidas Belts W-6280
  </name>
  <category>
   Belts
  </category>
  <size>
   S
  </size>
  <color>
   Зеленый
  </color>
  <material>
   Полиэстер
  </material>
  <price>
   706475
  </price>
  <rating>
   1.48
  </rating>
  <reviews>
   348022
  </reviews>
  <new>
   -
  </new>
  <exclusive>
   yes
  </exclusive>
  <sporty>
   no
  </sporty>
 </clothing>
 <clothing>
  <id>
   251574629
  </id>
  <name>
   Reebok Belts E-5474
  </name>
  <category>
   Belts
  </category>
  <size>
   XL
  </size>
  <color>
   Зеленый
  </color>
  <material>
   Полиэстер
  </material>
  <price>
   398560
  </price>
  <rating>
   1.6
  </rating>
  <reviews>
   30874
  </reviews>
  <new>
   -
  </new>
  <sporty>
   no
  </sporty>
 </clothing>
 <clothing>
  <id>
   829659618
  </id>
  <name>
   Vans Sweater L-6581
  </name>
  <category>
   Sweater
  </category>
  <size>
   L
  </size>
  <color>
   Желтый
  </color>
  <material>
   Кожа
  </material>
  <price>
   418159
  </price>
  <rating>
   2.79
  </rating>
  <reviews>
   441673
  </reviews>
  <new>
   -
  </new>
 </clothing>
 <clothing>
  <id>
   900377188
  </id>
  <name>
   Brooks Handbags L-4130
  </name>
  <category>
   Handbags
  </category>
  <size>
   XXL
  </size>
  <color>
   Оранжевый
  </color>
  <material>
   Хлопок
  </material>
  <price>
   248672
  </price>
  <rating>
   3.59
  </rating>
  <reviews>
   330706
  </reviews>
  <new>
   +
  </new>
  <exclusive>
   no
  </exclusive>
 </clothing>
 <clothing>
  <id>
   129299097
  </id>
  <name>
   Nike Shirt T-5511
  </name>
  <category>
   Shirt
  </category>
  <size>
   S
  </size>
  <color>
   Фиолетовый
  </color>
  <material>
   Хлопок
  </material>
  <price>
   945370
  </price>
  <rating>
   3.05
  </rating>
  <reviews>
   848341
  </reviews>
  <new>
   -
  </new>
  <exclusive>
   no
  </exclusive>
 </clothing>
 <clothing>
  <id>
   486087742
  </id>
  <name>
   Fila Pants X-3415
  </name>
  <category>
   Pants
  </category>
  <size>
   M
  </size>
  <color>
   Желтый
  </color>
  <material>
   Хлопок
  </material>
  <price>
   115732
  </price>
  <rating>
   2.89
  </rating>
  <reviews>
   42214
  </reviews>
  <exclusive>
   yes
  </exclusive>
 </clothing>
 <clothing>
  <id>
   824292546
  </id>
  <name>
   Lacoste Skirt F-2936
  </name>
  <category>
   Skirt
  </category>
  <size>
   S
  </size>
  <color>
   Желтый
  </color>
  <material>
   Шелк
  </material>
  <price>
   400899
  </price>
  <rating>
   4.91
  </rating>
  <reviews>
   962982
  </reviews>
  <new>
   -
  </new>
  <exclusive>
   yes
  </exclusive>
 </clothing>
 <clothing>
  <id>
   681266992
  </id>
  <name>
   Converse T-shirt U-7474
  </name>
  <category>
   T-shirt
  </category>
  <size>
   S
  </size>
  <color>
   Фиолетовый
  </color>
  <material>
   Кожа
  </material>
  <price>
   523832
  </price>
  <rating>
   4.71
  </rating>
  <reviews>
   768569
  </reviews>
  <exclusive>
   yes
  </exclusive>
  <sporty>
   yes
  </sporty>
 </clothing>
 <clothing>
  <id>
   250993087
  </id>
  <name>
   Converse Belts E-9729
  </name>
  <category>
   Belts
  </category>
  <size>
   XXL
  </size>
  <color>
   Желтый
  </color>
  <material>
   Лен
  </material>
  <price>
   556468
  </price>
  <rating>
   4.37
  </rating>
  <reviews>
   541347
  </reviews>
  <new>
   -
  </new>
  <exclusive>
   yes
  </exclusive>
 </clothing>
 <clothing>
  <id>
   567112273
  </id>
  <name>
   Adidas Belts T-2080
  </name>
  <category>
   Belts
  </category>
  <size>
   S
  </size>
  <color>
   Красный
  </color>
  <material>
   Вискоза
  </material>
  <price>
   260808
  </price>
  <rating>
   4.05
  </rating>
  <reviews>
   238737
  </reviews>
  <new>
   +
  </new>
  <exclusive>
   no
  </exclusive>
  <sporty>
   yes
  </sporty>
 </clothing>
 <clothing>
  <id>
   896936623
  </id>
  <name>
   PleinSport T-shirt J-1269
  </name>
  <category>
   T-shirt
  </category>
  <size>
   XXL
  </size>
  <color>
   Зеленый
  </color>
  <material>
   Хлопок
  </material>
  <price>
   621540
  </price>
  <rating>
   1.89
  </rating>
  <reviews>
   322654
  </reviews>
  <new>
   -
  </new>
  <exclusive>
   no
  </exclusive>
  <sporty>
   no
  </sporty>
 </clothing>
</clothing-items>
