<?xml version="1.0" encoding="utf-8"?>
<clothing-items>
 <clothing>
  <id>
   796644724
  </id>
  <name>
   Under Armour Handbags R-1274
  </name>
  <category>
   Handbags
  </category>
  <size>
   XL
  </size>
  <color>
   Желтый
  </color>
  <material>
   Вискоза
  </material>
  <price>
   818508
  </price>
  <rating>
   3.9
  </rating>
  <reviews>
   503197
  </reviews>
  <exclusive>
   no
  </exclusive>
  <sporty>
   no
  </sporty>
 </clothing>
 <clothing>
  <id>
   917039291
  </id>
  <name>
   Addidas Pants F-6189
  </name>
  <category>
   Pants
  </category>
  <size>
   XL
  </size>
  <color>
   Оранжевый
  </color>
  <material>
   Полиэстер
  </material>
  <price>
   292106
  </price>
  <rating>
   2.32
  </rating>
  <reviews>
   756986
  </reviews>
  <new>
   -
  </new>
  <exclusive>
   no
  </exclusive>
 </clothing>
 <clothing>
  <id>
   385026739
  </id>
  <name>
   Asics Shoes H-6217
  </name>
  <category>
   Shoes
  </category>
  <size>
   M
  </size>
  <color>
   Желтый
  </color>
  <material>
   Вискоза
  </material>
  <price>
   828118
  </price>
  <rating>
   1.82
  </rating>
  <reviews>
   146567
  </reviews>
  <sporty>
   no
  </sporty>
 </clothing>
 <clothing>
  <id>
   375504503
  </id>
  <name>
   Puma Blouse R-4521
  </name>
  <category>
   Blouse
  </category>
  <size>
   L
  </size>
  <color>
   Синий
  </color>
  <material>
   Лен
  </material>
  <price>
   511229
  </price>
  <rating>
   4.86
  </rating>
  <reviews>
   834728
  </reviews>
  <new>
   +
  </new>
  <sporty>
   yes
  </sporty>
 </clothing>
 <clothing>
  <id>
   234103942
  </id>
  <name>
   New Balance Pants J-4909
  </name>
  <category>
   Pants
  </category>
  <size>
   XXL
  </size>
  <color>
   Зеленый
  </color>
  <material>
   Нейлон
  </material>
  <price>
   941988
  </price>
  <rating>
   2.57
  </rating>
  <reviews>
   673755
  </reviews>
 </clothing>
 <clothing>
  <id>
   643401319
  </id>
  <name>
   Lacoste Umbrellas R-8681
  </name>
  <category>
   Umbrellas
  </category>
  <size>
   S
  </size>
  <color>
   Голубой
  </color>
  <material>
   Полиэстер
  </material>
  <price>
   755248
  </price>
  <rating>
   4.6
  </rating>
  <reviews>
   71153
  </reviews>
 </clothing>
 <clothing>
  <id>
   254472551
  </id>
  <name>
   Brooks Gloves Y-2096
  </name>
  <category>
   Gloves
  </category>
  <size>
   M
  </size>
  <color>
   Зеленый
  </color>
  <material>
   Хлопок
  </material>
  <price>
   800354
  </price>
  <rating>
   1.51
  </rating>
  <reviews>
   452537
  </reviews>
  <new>
   +
  </new>
  <sporty>
   no
  </sporty>
 </clothing>
 <clothing>
  <id>
   677010185
  </id>
  <name>
   Nike Blouse K-3540
  </name>
  <category>
   Blouse
  </category>
  <size>
   XXL
  </size>
  <color>
   Желтый
  </color>
  <material>
   Шерсть
  </material>
  <price>
   810088
  </price>
  <rating>
   1.48
  </rating>
  <reviews>
   947716
  </reviews>
  <exclusive>
   yes
  </exclusive>
  <sporty>
   yes
  </sporty>
 </clothing>
 <clothing>
  <id>
   528215423
  </id>
  <name>
   Adidas Shoes K-3080
  </name>
  <category>
   Shoes
  </category>
  <size>
   M
  </size>
  <color>
   Фиолетовый
  </color>
  <material>
   Нейлон
  </material>
  <price>
   948677
  </price>
  <rating>
   1.71
  </rating>
  <reviews>
   908487
  </reviews>
  <new>
   +
  </new>
  <exclusive>
   yes
  </exclusive>
  <sporty>
   no
  </sporty>
 </clothing>
 <clothing>
  <id>
   680786740
  </id>
  <name>
   PleinSport Hat A-5217
  </name>
  <category>
   Hat
  </category>
  <size>
   L
  </size>
  <color>
   Оранжевый
  </color>
  <material>
   Лен
  </material>
  <price>
   752041
  </price>
  <rating>
   2.51
  </rating>
  <reviews>
   858627
  </reviews>
  <new>
   -
  </new>
  <sporty>
   no
  </sporty>
 </clothing>
 <clothing>
  <id>
   301678069
  </id>
  <name>
   Brooks Blouse D-8308
  </name>
  <category>
   Blouse
  </category>
  <size>
   L
  </size>
  <color>
   Синий
  </color>
  <material>
   Шелк
  </material>
  <price>
   424375
  </price>
  <rating>
   1.57
  </rating>
  <reviews>
   225293
  </reviews>
  <new>
   -
  </new>
  <sporty>
   yes
  </sporty>
 </clothing>
 <clothing>
  <id>
   717136691
  </id>
  <name>
   DC Sweater M-9513
  </name>
  <category>
   Sweater
  </category>
  <size>
   XL
  </size>
  <color>
   Зеленый
  </color>
  <material>
   Кожа
  </material>
  <price>
   855323
  </price>
  <rating>
   4.36
  </rating>
  <reviews>
   723896
  </reviews>
  <new>
   +
  </new>
  <exclusive>
   yes
  </exclusive>
 </clothing>
 <clothing>
  <id>
   964705604
  </id>
  <name>
   Vans Gloves Z-8943
  </name>
  <category>
   Gloves
  </category>
  <size>
   XXL
  </size>
  <color>
   Синий
  </color>
  <material>
   Полиэстер
  </material>
  <price>
   458702
  </price>
  <rating>
   4.84
  </rating>
  <reviews>
   96407
  </reviews>
  <new>
   +
  </new>
  <sporty>
   no
  </sporty>
 </clothing>
 <clothing>
  <id>
   859043210
  </id>
  <name>
   Brooks Shoes X-9137
  </name>
  <category>
   Shoes
  </category>
  <size>
   L
  </size>
  <color>
   Оранжевый
  </color>
  <material>
   Полиэстер
  </material>
  <price>
   492423
  </price>
  <rating>
   3.78
  </rating>
  <reviews>
   861088
  </reviews>
  <exclusive>
   yes
  </exclusive>
  <sporty>
   no
  </sporty>
 </clothing>
 <clothing>
  <id>
   140194501
  </id>
  <name>
   Brooks Sweater U-6603
  </name>
  <category>
   Sweater
  </category>
  <size>
   XXL
  </size>
  <color>
   Голубой
  </color>
  <material>
   Лен
  </material>
  <price>
   485279
  </price>
  <rating>
   4.35
  </rating>
  <reviews>
   81782
  </reviews>
  <new>
   +
  </new>
  <exclusive>
   yes
  </exclusive>
  <sporty>
   no
  </sporty>
 </clothing>
 <clothing>
  <id>
   901317716
  </id>
  <name>
   Under Armour Shirt Z-3431
  </name>
  <category>
   Shirt
  </category>
  <size>
   M
  </size>
  <color>
   Красный
  </color>
  <material>
   Кожа
  </material>
  <price>
   818051
  </price>
  <rating>
   4.79
  </rating>
  <reviews>
   43121
  </reviews>
  <new>
   +
  </new>
  <exclusive>
   no
  </exclusive>
  <sporty>
   no
  </sporty>
 </clothing>
 <clothing>
  <id>
   187582462
  </id>
  <name>
   DC Socks T-9145
  </name>
  <category>
   Socks
  </category>
  <size>
   S
  </size>
  <color>
   Зеленый
  </color>
  <material>
   Кожа
  </material>
  <price>
   934125
  </price>
  <rating>
   2.32
  </rating>
  <reviews>
   735049
  </reviews>
 </clothing>
 <clothing>
  <id>
   149924412
  </id>
  <name>
   Reebok Socks B-5557
  </name>
  <category>
   Socks
  </category>
  <size>
   L
  </size>
  <color>
   Синий
  </color>
  <material>
   Шерсть
  </material>
  <price>
   906021
  </price>
  <rating>
   2.46
  </rating>
  <reviews>
   250416
  </reviews>
  <new>
   -
  </new>
 </clothing>
 <clothing>
  <id>
   502717234
  </id>
  <name>
   DC Shoes H-5840
  </name>
  <category>
   Shoes
  </category>
  <size>
   M
  </size>
  <color>
   Зеленый
  </color>
  <material>
   Лен
  </material>
  <price>
   164657
  </price>
  <rating>
   3.64
  </rating>
  <reviews>
   67680
  </reviews>
  <new>
   -
  </new>
  <sporty>
   yes
  </sporty>
 </clothing>
 <clothing>
  <id>
   852476213
  </id>
  <name>
   Asics Socks A-3449
  </name>
  <category>
   Socks
  </category>
  <size>
   S
  </size>
  <color>
   Красный
  </color>
  <material>
   Шерсть
  </material>
  <price>
   789971
  </price>
  <rating>
   2.5
  </rating>
  <reviews>
   888428
  </reviews>
  <new>
   +
  </new>
  <sporty>
   yes
  </sporty>
 </clothing>
 <clothing>
  <id>
   615549589
  </id>
  <name>
   DC T-shirt K-7584
  </name>
  <category>
   T-shirt
  </category>
  <size>
   XXL
  </size>
  <color>
   Оранжевый
  </color>
  <material>
   Хлопок
  </material>
  <price>
   392463
  </price>
  <rating>
   3.6
  </rating>
  <reviews>
   901269
  </reviews>
  <sporty>
   yes
  </sporty>
 </clothing>
 <clothing>
  <id>
   112970924
  </id>
  <name>
   Reebok Jacket I-6579
  </name>
  <category>
   Jacket
  </category>
  <size>
   XXL
  </size>
  <color>
   Желтый
  </color>
  <material>
   Полиэстер
  </material>
  <price>
   602882
  </price>
  <rating>
   4.49
  </rating>
  <reviews>
   41164
  </reviews>
  <exclusive>
   no
  </exclusive>
 </clothing>
 <clothing>
  <id>
   391666328
  </id>
  <name>
   Converse Sweater O-3502
  </name>
  <category>
   Sweater
  </category>
  <size>
   L
  </size>
  <color>
   Желтый
  </color>
  <material>
   Кожа
  </material>
  <price>
   820906
  </price>
  <rating>
   3.22
  </rating>
  <reviews>
   484332
  </reviews>
  <new>
   +
  </new>
  <exclusive>
   yes
  </exclusive>
  <sporty>
   yes
  </sporty>
 </clothing>
 <clothing>
  <id>
   691812034
  </id>
  <name>
   Lacoste Pants A-4406
  </name>
  <category>
   Pants
  </category>
  <size>
   M
  </size>
  <color>
   Желтый
  </color>
  <material>
   Лен
  </material>
  <price>
   836874
  </price>
  <rating>
   4.24
  </rating>
  <reviews>
   484514
  </reviews>
  <exclusive>
   no
  </exclusive>
  <sporty>
   yes
  </sporty>
 </clothing>
</clothing-items>
